rockhound/__init__.py
rockhound/_version.py
rockhound/bedmap2.py
rockhound/etopo1.py
rockhound/prem.py
rockhound/registry.py
rockhound/registry.txt
rockhound/seafloor.py
rockhound/slab2.py
rockhound/version.py
rockhound/tests/__init__.py
rockhound/tests/test_bedmap2.py
rockhound/tests/test_etopo1.py
rockhound/tests/test_prem.py
rockhound/tests/test_registry.py
rockhound/tests/test_seafloor.py
rockhound/tests/test_slab2.py
rockhound-0.2.0.dist-info/AUTHORS.md
rockhound-0.2.0.dist-info/LICENSE.txt
rockhound-0.2.0.dist-info/METADATA
rockhound-0.2.0.dist-info/WHEEL
rockhound-0.2.0.dist-info/top_level.txt
rockhound-0.2.0.dist-info/RECORD
