Metadata-Version: 2.1
Name: rockhound
Version: 0.2.0
Summary: Download geophysical models and load them as Python data structures.
Home-page: https://github.com/fatiando/rockhound
Author: The RockHound Developers
Author-email: leouieda@gmail.com
Maintainer: Leonardo Uieda
Maintainer-email: leouieda@gmail.com
License: BSD License
Platform: Any
Classifier: Development Status :: 3 - Alpha
Classifier: Intended Audience :: Science/Research
Classifier: Intended Audience :: Developers
Classifier: Intended Audience :: Education
Classifier: Topic :: Scientific/Engineering
Classifier: Topic :: Software Development :: Libraries
Classifier: Programming Language :: Python :: 3.6
Classifier: Programming Language :: Python :: 3.7
Classifier: License :: OSI Approved :: BSD License
Requires-Python: >=3.6
Requires-Dist: pooch (>=0.5)
Requires-Dist: xarray
Requires-Dist: pandas
Requires-Dist: rasterio
Requires-Dist: dask
Requires-Dist: netcdf4
